librus_scraper/announcements.py
librus_scraper/authorization.py
librus_scraper/cal.py
librus_scraper/grades.py
librus_scraper/messages.py
librus_scraper/other.py
librus_scraper/schedule.py
librus_scraper/__init__.py
librus_scraper-0.0.1.dist-info/DESCRIPTION.rst
librus_scraper-0.0.1.dist-info/METADATA
librus_scraper-0.0.1.dist-info/metadata.json
librus_scraper-0.0.1.dist-info/RECORD
librus_scraper-0.0.1.dist-info/top_level.txt
librus_scraper-0.0.1.dist-info/WHEEL
